{
  "name": "Gordon Reed",
  "age": 37,
  "address": {
    "street": "Sesej Glen",
    "city": "Fijnovro",
    "state": "NV",
    "zip": "76217"
  },
  "contact": {
    "phone": "(965) 676-9565",
    "servicePhone": "800539916"
  },
  "birthday": "1972-05-20T01:04:13.759Z",
  "ip": "162.52.242.125",
  "foo": "bar",
  "profile": {
    "about": "Ejwi ruv sohucewa hohgi pipva ip mih vespu wulam okkena wuncah gento mer ru newekres fab fesaoju. Vowiso manwikvub natsubug ruwvoho kukogaij nelian ibo irlofuz be odatov sodlunu woawrev dacofisu hur ubga uflalag hiz. Ojba puz bocbun sus dowdoaha isseh huliho mep kaameig najkabhi cob nirwi verem biuzaezu idehu ufe. Supalriw sizilidig teg cugav an kuhasi ke hef seku jeulbi ujlagfow rolacwo witobaza so pivwe wafejgi in zabini.",
    "bio": "Di opekadnot ururud vilunizuh kepmaj ico erkof to ba lotufilo bubco roctigcu te torepnu jef curughaz. Pec ca jinrefne zatuv cudte zen jinweki ago wokupav mulo meju hed kac ojoak. Hukipo valepe orgi olloc hofu vut raniwon cem cis ta tevaog socfuzef og woaze jut biwzalger icuvi sucuvsog. No el alajep diejka weadic li iw ko kilforji zaizhaf coow sec curejiv. Ib iz odilal okelo dub jait zoh law ane ojbacfo gimuk dutvavud na afozac nonewve. Pipgetap na do dosar sadeic rew faog odhen fugvej emege oredat zef difwa aruziud cofke."
  },
  "apiKey": "bee5728e05a13193ef2f52fa5b9f96d619944d12869a9fc0e1e96dc03c75e787",
  "currency": {
    "code": "BYR",
    "name": "Belarus Ruble"
  }
}