{
  "name": "Leon Singleton",
  "age": 39,
  "address": {
    "street": "Enne Path",
    "city": "Fuvicofaz",
    "state": "KS",
    "zip": "12977"
  },
  "contact": {
    "phone": "(213) 295-6427",
    "servicePhone": "800687782"
  },
  "birthday": "2004-03-01T12:04:39.863Z",
  "ip": "200.106.186.119",
  "foo": "bar",
  "profile": {
    "about": "Daki naowfe faucume arfula fuol jekig div jimicpu os hefeze etirehwo ar nevvole go imaute eceozma. Maarbu ledcuvos voguro sek heowufe ehucehul ripopjus eji ag gakhadcu le baffa cawhokeh acijow tukwip. Mibasec ovo epuvhal oj ogtuzi ip fursenan tazube er je zo nip. Komowo hic ta juvobpo wad mod zuowu zaoc uj fapedke uzu rarvissa epaehrot la urowime dev. Hifivhu wujivev esu miv tuhegec gugav welma jeb ibu novdu ogiz efene ruhdo. Oromor ninip eje owo gir balda vizig nihbazla dir vudapul opetodvov eglo epaaco rakacir. Soekilu nud le zof ajjovfit koliwu reswim afirta epeja god sunragiv uve.",
    "bio": "Binicgom jofaniboh wogpalevu or vul zu larikbum lapamu secuzcud ugaowemal um mecradci mak uzudaga. Vajihuana jirel oguim fanru suhju hovap ralwabap ju girdewa wec uceca kowohuho te lej ho. Firuvme hedavo woddori dumlefo cijab tu zaawusu agbawbid egu ubpogep huzan fuda posmugal cul pal. Tiwsoz mutcoh kodiv huj cutcib idokewfo ol asagaged ugcufor uhtozob muv buzdap ki fihuwavo. Pehe cagfiwab duw ci nep ihefiram nurbas nob wu haccep os ekcehu zerwo uv ziejavu puru okugeko. Ejhu vujbejeh pebov nahsa sujiz zifhejlip enberkas jujelpu gupwus ukejo ubkika wuuk ri imaco vup levozi. Woje barmez mef madadiw al rempa odosecru apikakbu dealav bucafo tez ce."
  },
  "apiKey": "726650b8227c95750ae912dcc3ba0137bcca9a529f896c4ede9e06f8797521f4",
  "currency": {
    "code": "PKR",
    "name": "Pakistan Rupee"
  }
}